nuclease_off_target/__init__.py
nuclease_off_target/constants.py
nuclease_off_target/crispr_target.py
nuclease_off_target/exceptions.py
nuclease_off_target/genomic_sequence.py
nuclease_off_target-0.3.0.dist-info/LICENSE
nuclease_off_target-0.3.0.dist-info/METADATA
nuclease_off_target-0.3.0.dist-info/WHEEL
nuclease_off_target-0.3.0.dist-info/top_level.txt
nuclease_off_target-0.3.0.dist-info/RECORD
